LICENSE
MANIFEST.in
README.rst
setup.cfg
setup.py
versioneer.py
tpDcc/__init__.py
tpDcc/libs/__init__.py
tpDcc/libs/math/__init__.py
tpDcc/libs/math/__logging__.ini
tpDcc/libs/math/__version__.py
tpDcc/libs/math/_version.py
tpDcc/libs/math/core/__init__.py
tpDcc/libs/math/core/bbox.py
tpDcc/libs/math/core/bezier.py
tpDcc/libs/math/core/consts.py
tpDcc/libs/math/core/dijkstra.py
tpDcc/libs/math/core/kdtree.py
tpDcc/libs/math/core/matrix.py
tpDcc/libs/math/core/octree.py
tpDcc/libs/math/core/scalar.py
tpDcc/libs/math/core/vec2.py
tpDcc/libs/math/core/vec3.py
tpDcc_libs_math.egg-info/PKG-INFO
tpDcc_libs_math.egg-info/SOURCES.txt
tpDcc_libs_math.egg-info/dependency_links.txt
tpDcc_libs_math.egg-info/not-zip-safe
tpDcc_libs_math.egg-info/requires.txt
tpDcc_libs_math.egg-info/top_level.txt