Metadata-Version: 2.1
Name: tpDcc-libs-math
Version: 0.0.1
Summary: Library that contains math related classes and functions for Python.
Home-page: https://github.com/tpDcc/tpDcc-libs-math
Author: Tomas Poveda
Author-email: tpovedatd@gmail.com
License: MIT
Platform: UNKNOWN
Provides-Extra: dev
Provides-Extra: test
